django_fagungis-0.1.1-py2.7-nspkg.pth
fagungis/example_fabfile.py
fagungis/tasks.py
fagungis/conf/nginx.conf
fagungis/conf/nginx_https.conf
fagungis/conf/supervisord.conf
fagungis/scripts/rungunicorn.sh
django_fagungis-0.1.1.dist-info/AUTHORS
django_fagungis-0.1.1.dist-info/LICENSE
django_fagungis-0.1.1.dist-info/METADATA
django_fagungis-0.1.1.dist-info/WHEEL
django_fagungis-0.1.1.dist-info/namespace_packages.txt
django_fagungis-0.1.1.dist-info/top_level.txt
django_fagungis-0.1.1.dist-info/RECORD
